pymars-0.10.0.dist-info/entry_points.txt
pymars-0.10.0.dist-info/RECORD
pymars-0.10.0.dist-info/METADATA
pymars-0.10.0.dist-info/top_level.txt
pymars-0.10.0.dist-info/LICENSE
pymars-0.10.0.dist-info/WHEEL
mars/_version.py
mars/opcodes.py
mars/__init__.py
mars/_utils.pyx
mars/supervisor.py
mars/worker.py
mars/utils.py
mars/config.py
mars/session.py
mars/_utils.pxd
mars/_resource.pyx
mars/_utils.cpython-38-aarch64-linux-gnu.so
mars/config.yml
mars/resource.py
mars/_resource.cpython-38-aarch64-linux-gnu.so
mars/typing.py
mars/conftest.py
mars/metrics/__init__.py
mars/metrics/api.py
mars/metrics/backends/__init__.py
mars/metrics/backends/metric.py
mars/metrics/backends/ray/__init__.py
mars/metrics/backends/ray/ray_metric.py
mars/metrics/backends/prometheus/__init__.py
mars/metrics/backends/prometheus/prometheus_metric.py
mars/metrics/backends/console/__init__.py
mars/metrics/backends/console/console_metric.py
mars/deploy/__init__.py
mars/deploy/utils.py
mars/deploy/kubedl/__init__.py
mars/deploy/kubedl/client.py
mars/deploy/kubedl/config.py
mars/deploy/oscar/__init__.py
mars/deploy/oscar/rayconfig.yml
mars/deploy/oscar/pool.py
mars/deploy/oscar/supervisor.py
mars/deploy/oscar/worker.py
mars/deploy/oscar/service.py
mars/deploy/oscar/session.py
mars/deploy/oscar/local.py
mars/deploy/oscar/ray.py
mars/deploy/oscar/cmdline.py
mars/deploy/oscar/config.yml
mars/deploy/oscar/base_config.yml
mars/deploy/yarn/__init__.py
mars/deploy/yarn/core.py
mars/deploy/yarn/supervisor.py
mars/deploy/yarn/worker.py
mars/deploy/yarn/client.py
mars/deploy/yarn/config.py
mars/deploy/yarn/config.yml
mars/deploy/kubernetes/__init__.py
mars/deploy/kubernetes/core.py
mars/deploy/kubernetes/supervisor.py
mars/deploy/kubernetes/worker.py
mars/deploy/kubernetes/client.py
mars/deploy/kubernetes/config.py
mars/deploy/kubernetes/config.yml
mars/serialization/aio.py
mars/serialization/core.cpython-38-aarch64-linux-gnu.so
mars/serialization/core.pyx
mars/serialization/__init__.py
mars/serialization/mars_objects.py
mars/serialization/arrow.py
mars/serialization/cuda.py
mars/serialization/numpy.py
mars/serialization/scipy.py
