Metadata-Version: 2.1
Name: pymars
Version: 0.10.0
Summary: MARS: a tensor-based unified framework for large-scale data computation.
Home-page: http://github.com/mars-project/mars
Author: Qin Xuye
Author-email: qin@qinxuye.me
Maintainer: Qin Xuye
Maintainer-email: qin@qinxuye.me
License: Apache License 2.0
Classifier: Operating System :: OS Independent
Classifier: Programming Language :: Python
Classifier: Programming Language :: Python :: 3
Classifier: Programming Language :: Python :: 3.7
Classifier: Programming Language :: Python :: 3.8
Classifier: Programming Language :: Python :: 3.9
Classifier: Programming Language :: Python :: 3.10
Classifier: Programming Language :: Python :: Implementation :: CPython
Classifier: Topic :: Software Development :: Libraries
License-File: LICENSE
Requires-Dist: numpy (>=1.14.0)
Requires-Dist: pandas (>=1.0.0)
Requires-Dist: scipy (>=1.0.0)
Requires-Dist: scikit-learn (>=0.20)
Requires-Dist: numexpr (>=2.6.4)
Requires-Dist: cloudpickle (>=1.5.0)
Requires-Dist: pyyaml (>=5.1)
Requires-Dist: psutil (>=5.9.0)
Requires-Dist: tornado (>=6.0)
Requires-Dist: sqlalchemy (>=1.2.0)
Requires-Dist: defusedxml (>=0.5.0)
Requires-Dist: tqdm (>=4.1.0)
Requires-Dist: pickle5 ; python_version < "3.8"
Requires-Dist: shared-memory38 (>=0.1.1) ; python_version < "3.8"
Requires-Dist: uvloop (>=0.14.0) ; sys_platform != "win32"
Provides-Extra: dev
Requires-Dist: cython (>=0.29) ; extra == 'dev'
Requires-Dist: pytest (>=3.5.0) ; extra == 'dev'
Requires-Dist: pytest-cov (>=2.5.0) ; extra == 'dev'
Requires-Dist: pytest-timeout (>=1.2.0) ; extra == 'dev'
Requires-Dist: pytest-forked (>=1.0) ; extra == 'dev'
Requires-Dist: pytest-asyncio (>=0.14.0) ; extra == 'dev'
Requires-Dist: flake8 (>=3.8.0) ; extra == 'dev'
Requires-Dist: black ; extra == 'dev'
Requires-Dist: mock (>=4.0.0) ; (python_version < "3.8") and extra == 'dev'
Provides-Extra: extra
Requires-Dist: pillow (>=7.0.0) ; extra == 'extra'
Requires-Dist: pyarrow (!=0.16.*,>=0.11.0) ; extra == 'extra'
Requires-Dist: lz4 (>=1.0.0) ; extra == 'extra'
Requires-Dist: fsspec (!=2022.8.0,>=2022.7.1) ; extra == 'extra'
Provides-Extra: kubernetes
Requires-Dist: kubernetes (>=10.0.0) ; extra == 'kubernetes'
Provides-Extra: ray
Requires-Dist: ray (>=1.8.0) ; extra == 'ray'
Provides-Extra: vineyard
Requires-Dist: vineyard (>=0.11.1) ; (sys_platform != "win32") and extra == 'vineyard'
